parallel_write/__init__.py
parallel_write/writer.py
parallel_write-0.0.10.dist-info/LICENSE
parallel_write-0.0.10.dist-info/METADATA
parallel_write-0.0.10.dist-info/WHEEL
parallel_write-0.0.10.dist-info/top_level.txt
parallel_write-0.0.10.dist-info/RECORD
