Metadata-Version: 2.1
Name: parallel-write
Version: 0.0.10
Summary: Writes to many open file objects in parallel.
Home-page: https://github.com/Mikata-Project/parallel_write
Author: NAGY, Attila
Author-email: nagy.attila@gmail.com
License: MIT License
Project-URL: webpage, https://github.com/Mikata-Project/parallel_write
Project-URL: Documentation, https://parallel-write.readthedocs.io/en/latest/
Project-URL: Changelog, https://github.com/Mikata-Project/parallel_write/blob/master/docs/CHANGELOG.rst
Project-URL: Issue Tracker, https://github.com/Mikata-Project/parallel_write/issues
Project-URL: Discussion Forum, https://github.com/Mikata-Project/parallel_write/discussions
Keywords: io,parallel,distributed,multiple
Platform: UNKNOWN
Classifier: Development Status :: 5 - Production/Stable
Classifier: License :: OSI Approved :: MIT License
Classifier: Natural Language :: English
Classifier: Operating System :: POSIX
Classifier: Programming Language :: Python
Requires-Python: >=3.5
License-File: LICENSE
